hello/__init__.py
hello/saythirumalai.py
sayhellotoyou-0.0.1.dist-info/METADATA
sayhellotoyou-0.0.1.dist-info/WHEEL
sayhellotoyou-0.0.1.dist-info/top_level.txt
sayhellotoyou-0.0.1.dist-info/RECORD
